metalcompute.cpython-39-darwin.so
metalcompute-0.2.9.data/scripts/metalcompute-measure
metalcompute-0.2.9.data/scripts/metalcompute-mandelbrot
metalcompute-0.2.9.data/scripts/metalcompute-raymarch
metalcompute-0.2.9.data/scripts/metalcompute-pipe
metalcompute-0.2.9.dist-info/RECORD
metalcompute-0.2.9.dist-info/LICENSE
metalcompute-0.2.9.dist-info/WHEEL
metalcompute-0.2.9.dist-info/top_level.txt
metalcompute-0.2.9.dist-info/METADATA
