Metadata-Version: 2.1
Name: metalcompute
Version: 0.2.9
Summary: A python library to run metal compute kernels on macOS
Home-page: https://github.com/baldand/py-metal-compute
Author: Andrew Baldwin
Author-email: metalcompute@dehabit.info
License: UNKNOWN
Project-URL: Issue Tracker, https://github.com/baldand/py-metal-compute/issues
Platform: UNKNOWN
Classifier: Development Status :: 3 - Alpha
Classifier: Programming Language :: Python :: 3
Classifier: License :: OSI Approved :: MIT License
Classifier: Operating System :: MacOS :: MacOS X
Classifier: Environment :: GPU
Requires-Python: >=3.9
License-File: LICENSE
